action_updater/__init__.py
action_updater/defaults.py
action_updater/logger.py
action_updater/settings.yml
action_updater/version.py
action_updater/client/__init__.py
action_updater/client/config.py
action_updater/client/detect.py
action_updater/client/helpers.py
action_updater/client/listing.py
action_updater/client/update.py
action_updater/main/__init__.py
action_updater/main/action.py
action_updater/main/client.py
action_updater/main/github.py
action_updater/main/schemas.py
action_updater/main/settings.py
action_updater/main/updater.py
action_updater/main/updaters/__init__.py
action_updater/main/updaters/savestate/__init__.py
action_updater/main/updaters/savestate/update.py
action_updater/main/updaters/setenv/__init__.py
action_updater/main/updaters/setenv/update.py
action_updater/main/updaters/setoutput/__init__.py
action_updater/main/updaters/setoutput/update.py
action_updater/main/updaters/version/__init__.py
action_updater/main/updaters/version/update.py
action_updater/tests/helpers.py
action_updater/tests/test_updaters.py
action_updater/tests/data/save-state-after.yaml
action_updater/tests/data/save-state-before.yaml
action_updater/tests/data/set-env-after.yaml
action_updater/tests/data/set-env-before.yaml
action_updater/tests/data/set-output-after.yaml
action_updater/tests/data/set-output-before.yaml
action_updater/tests/data/version-after.yaml
action_updater/tests/data/version-before.yaml
action_updater/utils/__init__.py
action_updater/utils/custom_yaml.py
action_updater/utils/fileio.py
action_updater/utils/terminal.py
action_updater-0.0.16.dist-info/LICENSE
action_updater-0.0.16.dist-info/METADATA
action_updater-0.0.16.dist-info/WHEEL
action_updater-0.0.16.dist-info/entry_points.txt
action_updater-0.0.16.dist-info/top_level.txt
action_updater-0.0.16.dist-info/RECORD
