Metadata-Version: 2.1
Name: action-updater
Version: 0.0.16
Summary: Update deprecated command, versions, and other for GitHub actions
Home-page: https://github.com/vsoch/action-updater
Author: Vanessa Sochat
Author-email: vsoch@users.noreply.github.com
Maintainer: Vanessa Sochat
License: LICENSE
Keywords: github,actions,updater
Classifier: Intended Audience :: Science/Research
Classifier: Intended Audience :: Developers
Classifier: License :: OSI Approved :: Mozilla Public License 2.0 (MPL 2.0)
Classifier: Programming Language :: Python
Classifier: Topic :: Software Development
Classifier: Topic :: Scientific/Engineering
Classifier: Operating System :: Unix
Classifier: Programming Language :: Python :: 3.7
License-File: LICENSE
Requires-Dist: pipelib
Requires-Dist: jsonschema
Requires-Dist: ruamel.yaml
Requires-Dist: rich
Requires-Dist: pyyaml
Requires-Dist: requests
Requires-Dist: packaging
Provides-Extra: all
Requires-Dist: pipelib ; extra == 'all'
Requires-Dist: jsonschema ; extra == 'all'
Requires-Dist: ruamel.yaml ; extra == 'all'
Requires-Dist: rich ; extra == 'all'
Requires-Dist: pyyaml ; extra == 'all'
Requires-Dist: requests ; extra == 'all'
Requires-Dist: packaging ; extra == 'all'
Requires-Dist: pytest (>=4.6.2) ; extra == 'all'
